README.txt
setup.py
cs/__init__.py
cs.navigation.egg-info/PKG-INFO
cs.navigation.egg-info/SOURCES.txt
cs.navigation.egg-info/dependency_links.txt
cs.navigation.egg-info/entry_points.txt
cs.navigation.egg-info/namespace_packages.txt
cs.navigation.egg-info/not-zip-safe
cs.navigation.egg-info/requires.txt
cs.navigation.egg-info/top_level.txt
cs/navigation/__init__.py
cs/navigation/configure.zcml
cs/navigation/rebuild_i18n.sh
cs/navigation/tests.py
cs/navigation/version.txt
cs/navigation/locales/cs.navigation-manual.pot
cs/navigation/locales/cs.navigation.pot
cs/navigation/locales/es/LC_MESSAGES/cs.navigation.mo
cs/navigation/locales/es/LC_MESSAGES/cs.navigation.po
cs/navigation/locales/eu/LC_MESSAGES/cs.navigation.mo
cs/navigation/locales/eu/LC_MESSAGES/cs.navigation.po
cs/navigation/portlets/__init__.py
cs/navigation/portlets/configure.zcml
cs/navigation/portlets/navigation.pt
cs/navigation/portlets/navigation.py
cs/navigation/portlets/navigation_recurse.pt
cs/navigation/portlets/test.pt
cs/navigation/profiles/default/portlets.xml
docs/HISTORY.txt
docs/INSTALL.txt
docs/LICENSE.GPL
docs/LICENSE.txt