Metadata-Version: 1.1
Name: cs.navigation
Version: 0.3
Summary: Simple navigation portlet based on plone's but with additional markup checks
Home-page: http://code.codesyntax.com/private/cs.navigation
Author: CodeSyntax
Author-email: mlarreategi@codesyntax.com
License: GPL
Keywords: plone portlets navigation
Platform: UNKNOWN
Classifier: Framework :: Plone
Classifier: Framework :: Zope2
Classifier: Framework :: Zope3
Classifier: Programming Language :: Python
Classifier: Topic :: Software Development :: Libraries :: Python Modules
